radar_api/__init__.py
radar_api/_config.py
radar_api/_version.py
radar_api/checks.py
radar_api/configs.py
radar_api/download.py
radar_api/filter.py
radar_api/info.py
radar_api/io.py
radar_api/readers.py
radar_api/search.py
radar_api/etc/network/FMI.yaml
radar_api/etc/network/IDEAM.yaml
radar_api/etc/network/NEXRAD.yaml
radar_api/etc/radar/FMI/fianj.yaml
radar_api/etc/radar/FMI/fiika.yaml
radar_api/etc/radar/FMI/fikan.yaml
radar_api/etc/radar/FMI/fikes.yaml
radar_api/etc/radar/FMI/fikor.yaml
radar_api/etc/radar/FMI/fikuo.yaml
radar_api/etc/radar/FMI/filuo.yaml
radar_api/etc/radar/FMI/finur.yaml
radar_api/etc/radar/FMI/fipet.yaml
radar_api/etc/radar/FMI/fiuta.yaml
radar_api/etc/radar/FMI/fivan.yaml
radar_api/etc/radar/FMI/fivih.yaml
radar_api/etc/radar/FMI/fivim.yaml
radar_api/etc/radar/IDEAM/Barrancabermeja.yaml
radar_api/etc/radar/IDEAM/Bogota.yaml
radar_api/etc/radar/IDEAM/Carimagua.yaml
radar_api/etc/radar/IDEAM/Corozal.yaml
radar_api/etc/radar/IDEAM/Guaviare.yaml
radar_api/etc/radar/IDEAM/Munchique.yaml
radar_api/etc/radar/IDEAM/San_Andres.yaml
radar_api/etc/radar/IDEAM/Tablazo.yaml
radar_api/etc/radar/IDEAM/santa_elena.yaml
radar_api/etc/radar/NEXRAD/DAN1.yaml
radar_api/etc/radar/NEXRAD/DOP1.yaml
radar_api/etc/radar/NEXRAD/FOP1.yaml
radar_api/etc/radar/NEXRAD/KABR.yaml
radar_api/etc/radar/NEXRAD/KABX.yaml
radar_api/etc/radar/NEXRAD/KAKQ.yaml
radar_api/etc/radar/NEXRAD/KAMA.yaml
radar_api/etc/radar/NEXRAD/KAMX.yaml
radar_api/etc/radar/NEXRAD/KAPX.yaml
radar_api/etc/radar/NEXRAD/KARX.yaml
radar_api/etc/radar/NEXRAD/KATX.yaml
radar_api/etc/radar/NEXRAD/KBBX.yaml
radar_api/etc/radar/NEXRAD/KBGM.yaml
radar_api/etc/radar/NEXRAD/KBHX.yaml
radar_api/etc/radar/NEXRAD/KBIS.yaml
radar_api/etc/radar/NEXRAD/KBLX.yaml
radar_api/etc/radar/NEXRAD/KBMX.yaml
radar_api/etc/radar/NEXRAD/KBOX.yaml
radar_api/etc/radar/NEXRAD/KBRO.yaml
radar_api/etc/radar/NEXRAD/KBUF.yaml
radar_api/etc/radar/NEXRAD/KBYX.yaml
radar_api/etc/radar/NEXRAD/KCAE.yaml
radar_api/etc/radar/NEXRAD/KCBW.yaml
radar_api-0.1.0.dist-info/LICENSE
radar_api-0.1.0.dist-info/METADATA
radar_api-0.1.0.dist-info/WHEEL
radar_api-0.1.0.dist-info/top_level.txt
radar_api-0.1.0.dist-info/RECORD
