Metadata-Version: 2.2
Name: radar_api
Version: 0.1.0
Summary: Python software to retrieve weather radar data from cloud buckets
Author-email: Gionata Ghiggi <gionata.ghiggi@epfl.ch>
License: MIT License
Project-URL: homepage, https://github.com/ghiggi/radar_api
Project-URL: repository, https://github.com/ghiggi/radar_api
Project-URL: source, https://github.com/ghiggi/radar_api
Project-URL: tracker, https://github.com/ghiggi/radar_api/issues
Project-URL: documentation, https://radar-api.readthedocs.io
Project-URL: changelog, https://github.com/ghiggi/radar_api/blob/main/CHANGELOG.md
Keywords: Weather,Radar,Precipitation,NEXRAD,FMI
Classifier: Development Status :: 5 - Production/Stable
Classifier: Intended Audience :: Science/Research
Classifier: Intended Audience :: Education
Classifier: License :: OSI Approved :: MIT License
Classifier: Natural Language :: English
Classifier: Operating System :: OS Independent
Classifier: Operating System :: Unix
Classifier: Operating System :: Microsoft
Classifier: Operating System :: MacOS
Classifier: Programming Language :: Python
Classifier: Programming Language :: Python :: 3
Classifier: Programming Language :: Python :: 3 :: Only
Classifier: Programming Language :: Python :: 3.10
Classifier: Programming Language :: Python :: 3.11
Classifier: Programming Language :: Python :: 3.12
Classifier: Programming Language :: Python :: 3.13
Classifier: Topic :: Scientific/Engineering
Classifier: Topic :: Scientific/Engineering :: Atmospheric Science
Classifier: Topic :: Scientific/Engineering :: GIS
Classifier: Topic :: Scientific/Engineering :: Hydrology
Classifier: Topic :: Scientific/Engineering :: Image Processing
Requires-Python: >=3.10
License-File: LICENSE
Requires-Dist: fsspec
Requires-Dist: s3fs
Requires-Dist: pyyaml
Requires-Dist: donfig
Requires-Dist: trollsift
Requires-Dist: numpy
Requires-Dist: pandas
Requires-Dist: tqdm
Provides-Extra: dev
Requires-Dist: pre-commit; extra == "dev"
Requires-Dist: loghub; extra == "dev"
Requires-Dist: black[jupyter]; extra == "dev"
Requires-Dist: blackdoc; extra == "dev"
Requires-Dist: codespell; extra == "dev"
Requires-Dist: ruff; extra == "dev"
Requires-Dist: pytest; extra == "dev"
Requires-Dist: pytest-cov; extra == "dev"
Requires-Dist: pytest-mock; extra == "dev"
Requires-Dist: pytest-check; extra == "dev"
Requires-Dist: pytest-sugar; extra == "dev"
Requires-Dist: pytest-watcher; extra == "dev"
Requires-Dist: deepdiff; extra == "dev"
Requires-Dist: pip-tools; extra == "dev"
Requires-Dist: bumpver; extra == "dev"
Requires-Dist: twine; extra == "dev"
Requires-Dist: wheel; extra == "dev"
Requires-Dist: build; extra == "dev"
Requires-Dist: setuptools>=61.0.0; extra == "dev"
Requires-Dist: sphinx; extra == "dev"
Requires-Dist: sphinx-gallery; extra == "dev"
Requires-Dist: sphinx-book-theme; extra == "dev"
Requires-Dist: nbsphinx; extra == "dev"
Requires-Dist: sphinx_mdinclude; extra == "dev"
